p4submodule/__init__.py
p4submodule/cli.py
p4submodule/config_file.py
p4submodule/p4_context.py
p4submodule/submodule.py
p4submodule-1.1.0.dist-info/METADATA
p4submodule-1.1.0.dist-info/WHEEL
p4submodule-1.1.0.dist-info/entry_points.txt
p4submodule-1.1.0.dist-info/licenses/LICENSE
p4submodule-1.1.0.dist-info/licenses/LICENSES/Apache-2.0.txt
p4submodule-1.1.0.dist-info/RECORD
