Metadata-Version: 2.4
Name: p4submodule
Version: 1.1.0
Summary: A tool for managing git repositories inside of Perforce depots
License-Expression: Apache-2.0
License-File: LICENSE
License-File: LICENSES/Apache-2.0.txt
Author: Colden Cullen
Author-email: <ccullen@secretdimension.com>
Requires-Python: >=3.11
Classifier: Environment :: Console
Classifier: Intended Audience :: Developers
Classifier: Topic :: Software Development :: Version Control
Classifier: Topic :: Software Development :: Version Control :: Git
Requires-Dist: click (==8.2.1)
Requires-Dist: msgspec (==0.19.0)
Requires-Dist: p4python (==2025.1.2767466)
Requires-Dist: paramiko (==4.0.0)
Requires-Dist: pygit2 (==1.18.1)
Requires-Dist: tomlkit (==0.13.3)
Project-URL: Repository, https://github.com/secretdimension/p4submodule
